task/__init__.py
task/__main__.py
task/__version__.py
task_planner-1.2.3.dist-info/LICENSE
task_planner-1.2.3.dist-info/METADATA
task_planner-1.2.3.dist-info/WHEEL
task_planner-1.2.3.dist-info/top_level.txt
task_planner-1.2.3.dist-info/RECORD
