Metadata-Version: 2.1
Name: task-planner
Version: 1.2.3
Summary: A task planner for the terminal.
Home-page: https://github.com/yannickkirschen/task
Author: Yannick Kirschen
Author-email: github.yannickkirschen@protonmail.com
License: MIT
Platform: UNKNOWN
Classifier: Programming Language :: Python :: 3
Classifier: License :: OSI Approved :: MIT License
Classifier: Operating System :: OS Independent
Classifier: Operating System :: OS Independent
Classifier: Intended Audience :: Developers
Classifier: Natural Language :: English
